tests/__init__.py
tests/tests_topsis.py
topsis/__init__.py
topsis/topsis.py
Abhinav_102103284_TOPSIS-0.1.0.dist-info/METADATA
Abhinav_102103284_TOPSIS-0.1.0.dist-info/WHEEL
Abhinav_102103284_TOPSIS-0.1.0.dist-info/entry_points.txt
Abhinav_102103284_TOPSIS-0.1.0.dist-info/top_level.txt
Abhinav_102103284_TOPSIS-0.1.0.dist-info/RECORD
